{"/*":["X-Frame-Options: DENY","X-XSS-Protection: 1; mode=block","X-Content-Type-Options: nosniff","Referrer-Policy: same-origin"],"/styles.de6eba0b38120112eda5.css":["Cache-Control: public, max-age=31536000, immutable"],"/022d3153bf09c36cd784dcdb36ffbd187f9c96d7-1a783bd96020054159f5.js":["Cache-Control: public, max-age=31536000, immutable"],"/component---src-templates-blog-post-tsx-c2864ab57766139bd924.js":["Cache-Control: public, max-age=31536000, immutable"],"/component---src-pages-404-tsx-a3798eb0f745f7e21acf.js":["Cache-Control: public, max-age=31536000, immutable"],"/component---src-pages-index-tsx-63703333d3a263c3641c.js":["Cache-Control: public, max-age=31536000, immutable"],"/webpack-runtime-3a057a0086174fbf8a0d.js":["Cache-Control: public, max-age=31536000, immutable"],"/framework-f53a5bf2055fd5c1e68b.js":["Cache-Control: public, max-age=31536000, immutable"],"/app-d21e4d111c1844bb705d.js":["Cache-Control: public, max-age=31536000, immutable"],"/static/*":["Cache-Control: public, max-age=31536000, immutable"],"/sw.js":["Cache-Control: public, max-age=0, must-revalidate"],"/test4/1":["Link: </webpack-runtime-3a057a0086174fbf8a0d.js>; rel=preload; as=script; nopush","Link: </framework-f53a5bf2055fd5c1e68b.js>; rel=preload; as=script; nopush","Link: </app-d21e4d111c1844bb705d.js>; rel=preload; as=script; nopush","Link: </022d3153bf09c36cd784dcdb36ffbd187f9c96d7-1a783bd96020054159f5.js>; rel=preload; as=script; nopush","Link: </component---src-templates-blog-post-tsx-c2864ab57766139bd924.js>; rel=preload; as=script; nopush","Link: </page-data/app-data.json>; rel=preload; as=fetch; crossorigin; nopush","Link: </page-data/test4/1/page-data.json>; rel=preload; as=fetch; crossorigin; nopush"],"/test1/hihi":["Link: </webpack-runtime-3a057a0086174fbf8a0d.js>; rel=preload; as=script; nopush","Link: </framework-f53a5bf2055fd5c1e68b.js>; rel=preload; as=script; nopush","Link: </app-d21e4d111c1844bb705d.js>; rel=preload; as=script; nopush","Link: </022d3153bf09c36cd784dcdb36ffbd187f9c96d7-1a783bd96020054159f5.js>; rel=preload; as=script; nopush","Link: </component---src-templates-blog-post-tsx-c2864ab57766139bd924.js>; rel=preload; as=script; nopush","Link: </page-data/app-data.json>; rel=preload; as=fetch; crossorigin; nopush","Link: </page-data/test1/hihi/page-data.json>; rel=preload; as=fetch; crossorigin; nopush"],"/hi/1":["Link: </webpack-runtime-3a057a0086174fbf8a0d.js>; rel=preload; as=script; nopush","Link: </framework-f53a5bf2055fd5c1e68b.js>; rel=preload; as=script; nopush","Link: </app-d21e4d111c1844bb705d.js>; rel=preload; as=script; nopush","Link: </022d3153bf09c36cd784dcdb36ffbd187f9c96d7-1a783bd96020054159f5.js>; rel=preload; as=script; nopush","Link: </component---src-templates-blog-post-tsx-c2864ab57766139bd924.js>; rel=preload; as=script; nopush","Link: </page-data/app-data.json>; rel=preload; as=fetch; crossorigin; nopush","Link: </page-data/hi/1/page-data.json>; rel=preload; as=fetch; crossorigin; nopush"],"/test2/second":["Link: </webpack-runtime-3a057a0086174fbf8a0d.js>; rel=preload; as=script; nopush","Link: </framework-f53a5bf2055fd5c1e68b.js>; rel=preload; as=script; nopush","Link: </app-d21e4d111c1844bb705d.js>; rel=preload; as=script; nopush","Link: </022d3153bf09c36cd784dcdb36ffbd187f9c96d7-1a783bd96020054159f5.js>; rel=preload; as=script; nopush","Link: </component---src-templates-blog-post-tsx-c2864ab57766139bd924.js>; rel=preload; as=script; nopush","Link: </page-data/app-data.json>; rel=preload; as=fetch; crossorigin; nopush","Link: </page-data/test2/second/page-data.json>; rel=preload; as=fetch; crossorigin; nopush"],"/hi/2":["Link: </webpack-runtime-3a057a0086174fbf8a0d.js>; rel=preload; as=script; nopush","Link: </framework-f53a5bf2055fd5c1e68b.js>; rel=preload; as=script; nopush","Link: </app-d21e4d111c1844bb705d.js>; rel=preload; as=script; nopush","Link: </022d3153bf09c36cd784dcdb36ffbd187f9c96d7-1a783bd96020054159f5.js>; rel=preload; as=script; nopush","Link: </component---src-templates-blog-post-tsx-c2864ab57766139bd924.js>; rel=preload; as=script; nopush","Link: </page-data/app-data.json>; rel=preload; as=fetch; crossorigin; nopush","Link: </page-data/hi/2/page-data.json>; rel=preload; as=fetch; crossorigin; nopush"],"/hi/aa":["Link: </webpack-runtime-3a057a0086174fbf8a0d.js>; rel=preload; as=script; nopush","Link: </framework-f53a5bf2055fd5c1e68b.js>; rel=preload; as=script; nopush","Link: </app-d21e4d111c1844bb705d.js>; rel=preload; as=script; nopush","Link: </022d3153bf09c36cd784dcdb36ffbd187f9c96d7-1a783bd96020054159f5.js>; rel=preload; as=script; nopush","Link: </component---src-templates-blog-post-tsx-c2864ab57766139bd924.js>; rel=preload; as=script; nopush","Link: </page-data/app-data.json>; rel=preload; as=fetch; crossorigin; nopush","Link: </page-data/hi/aa/page-data.json>; rel=preload; as=fetch; crossorigin; nopush"],"/test1/first":["Link: </webpack-runtime-3a057a0086174fbf8a0d.js>; rel=preload; as=script; nopush","Link: </framework-f53a5bf2055fd5c1e68b.js>; rel=preload; as=script; nopush","Link: </app-d21e4d111c1844bb705d.js>; rel=preload; as=script; nopush","Link: </022d3153bf09c36cd784dcdb36ffbd187f9c96d7-1a783bd96020054159f5.js>; rel=preload; as=script; nopush","Link: </component---src-templates-blog-post-tsx-c2864ab57766139bd924.js>; rel=preload; as=script; nopush","Link: </page-data/app-data.json>; rel=preload; as=fetch; crossorigin; nopush","Link: </page-data/test1/first/page-data.json>; rel=preload; as=fetch; crossorigin; nopush"],"/test3/third":["Link: </webpack-runtime-3a057a0086174fbf8a0d.js>; rel=preload; as=script; nopush","Link: </framework-f53a5bf2055fd5c1e68b.js>; rel=preload; as=script; nopush","Link: </app-d21e4d111c1844bb705d.js>; rel=preload; as=script; nopush","Link: </022d3153bf09c36cd784dcdb36ffbd187f9c96d7-1a783bd96020054159f5.js>; rel=preload; as=script; nopush","Link: </component---src-templates-blog-post-tsx-c2864ab57766139bd924.js>; rel=preload; as=script; nopush","Link: </page-data/app-data.json>; rel=preload; as=fetch; crossorigin; nopush","Link: </page-data/test3/third/page-data.json>; rel=preload; as=fetch; crossorigin; nopush"],"/404/":["Link: </webpack-runtime-3a057a0086174fbf8a0d.js>; rel=preload; as=script; nopush","Link: </framework-f53a5bf2055fd5c1e68b.js>; rel=preload; as=script; nopush","Link: </app-d21e4d111c1844bb705d.js>; rel=preload; as=script; nopush","Link: </component---src-pages-404-tsx-a3798eb0f745f7e21acf.js>; rel=preload; as=script; nopush","Link: </page-data/app-data.json>; rel=preload; as=fetch; crossorigin; nopush","Link: </page-data/404/page-data.json>; rel=preload; as=fetch; crossorigin; nopush"],"/404.html":["Link: </webpack-runtime-3a057a0086174fbf8a0d.js>; rel=preload; as=script; nopush","Link: </framework-f53a5bf2055fd5c1e68b.js>; rel=preload; as=script; nopush","Link: </app-d21e4d111c1844bb705d.js>; rel=preload; as=script; nopush","Link: </component---src-pages-404-tsx-a3798eb0f745f7e21acf.js>; rel=preload; as=script; nopush","Link: </page-data/app-data.json>; rel=preload; as=fetch; crossorigin; nopush","Link: </page-data/404.html/page-data.json>; rel=preload; as=fetch; crossorigin; nopush"],"/":["Link: </webpack-runtime-3a057a0086174fbf8a0d.js>; rel=preload; as=script; nopush","Link: </framework-f53a5bf2055fd5c1e68b.js>; rel=preload; as=script; nopush","Link: </app-d21e4d111c1844bb705d.js>; rel=preload; as=script; nopush","Link: </022d3153bf09c36cd784dcdb36ffbd187f9c96d7-1a783bd96020054159f5.js>; rel=preload; as=script; nopush","Link: </component---src-pages-index-tsx-63703333d3a263c3641c.js>; rel=preload; as=script; nopush","Link: </page-data/app-data.json>; rel=preload; as=fetch; crossorigin; nopush","Link: </page-data/index/page-data.json>; rel=preload; as=fetch; crossorigin; nopush"]}